multilearn/__init__.py
multilearn/models.py
multilearn/plots.py
multilearn/utils.py
multilearn-0.0.9.dist-info/LICENSE
multilearn-0.0.9.dist-info/METADATA
multilearn-0.0.9.dist-info/WHEEL
multilearn-0.0.9.dist-info/top_level.txt
multilearn-0.0.9.dist-info/RECORD
