Metadata-Version: 2.1
Name: multilearn
Version: 0.0.9
Summary: Multi-task learning with Pytorch.
Home-page: https://github.com/leschultz/multilearn
Author: Lane E. Schultz
Author-email: laneenriqueschultz@gmail.com
Classifier: Programming Language :: Python :: 3
Classifier: License :: OSI Approved :: MIT License
Classifier: Operating System :: OS Independent
Requires-Python: >=3.10
License-File: LICENSE
Requires-Dist: torch
Requires-Dist: scikit-learn
Requires-Dist: lightning
Requires-Dist: pandas
Requires-Dist: matplotlib
Requires-Dist: dill
Requires-Dist: pytest
